{
  "title": "Our Products",
  "content": [
    {
      "_id": 1,
      "image": "../images/crystal1.jpg",
      "name": "Green Flurite",
      "price": 15
    },
    {
      "_id": 2,
      "image": "../images/crystal2.jpg",
      "name": "Rose Quartz",
      "price": 15
    },
    {
      "_id": 3,
      "image": "../images/crystal3.jpg",
      "name": "Obsedian",
      "price": 15
    },
    {
      "_id": 4,
      "image": "../images/crystal4.jpg",
      "name": "Opal",
      "price": 15
    },
    {
      "_id": 5,
      "image": "../images/crystal1.jpg",
      "name": "Amethyst",
      "price": 15
    }
  ],
  "testimonials": [
    {
      "_id": 1,
      "author": "John Doe",
      "review": "One of the best crystals I've ever seen."
    },
    {
      "_id": 2,
      "author": "Jane Doe",
      "review": "Cannot get any better than this."
    },
    {
      "_id": 3,
      "author": "Amazing Quality",
      "review": "I got the Obsidian Cystal necklace for my husband and it was absolutely worth it."
    }
  ]
}
